flash_attention_srf/__init__.py
flash_attention_srf/ops/__init__.py
flash_attention_srf/ops/torch/__init__.py
flash_attention_srf/ops/torch/attention.py
flash_attention_srf/ops/torch/kernels.py
flash_attention_srf/ops/torch/srfs.py
flash_attention_srf/ops/triton/__init__.py
flash_attention_srf/ops/triton/flash_attn.py
flash_attention_srf/ops/triton/flash_attn_mosaic.py
flash_attention_srf-0.0.8.dist-info/LICENSE
flash_attention_srf-0.0.8.dist-info/METADATA
flash_attention_srf-0.0.8.dist-info/WHEEL
flash_attention_srf-0.0.8.dist-info/top_level.txt
flash_attention_srf-0.0.8.dist-info/RECORD
