Metadata-Version: 2.1
Name: flash-attention-srf
Version: 0.0.8
Summary: Softmax-less Flash Attention w/ SRFs
Home-page: https://github.com/alexjlevenston/flash-attention-srf
Author: Alexander Levenston
Author-email: alexlevenston2021@gmail.com
License: UNKNOWN
Platform: UNKNOWN
Classifier: Programming Language :: Python :: 3
Classifier: License :: OSI Approved :: MIT License
Classifier: Operating System :: OS Independent
Requires-Python: >=3.6
License-File: LICENSE
Requires-Dist: scipy
Requires-Dist: torch
